{
  "lxx": 109,
  "title": "A Psalm of David. The Lord said to my Lord, Sit thou on my right hand, until I make thine enemies thy footstool.",
  "verses": [
    {
      "n": 1,
      "t": "The Lord shall send out a rod of power for thee out of Sion: rule thou in the midst of thine enemies."
    },
    {
      "n": 2,
      "t": "With thee is dominion in the day of thy power, in the splendours of thy saints: I have begotten thee from the womb before the morning."
    },
    {
      "n": 3,
      "t": "The Lord sware, and will not repent, Thou art a priest for ever, after the order of Melchisedec."
    },
    {
      "n": 4,
      "t": "The Lord at thy right hand has dashed in pieces kings in the day of his wrath."
    },
    {
      "n": 5,
      "t": "He shall judge among the nations, he shall fill up the number of corpses, he shall crush the heads of many on the earth."
    },
    {
      "n": 6,
      "t": "He shall drink of the brook in the way; therefore shall he lift up the head. ✡109:1 Mat. 22. 44."
    }
  ]
}